[{"COMMON_ID":"locale001","M_HREFLANG_CODE":"sl-SI","M_COUNTRY_NATIVE":"Slovenija","M_COUNTRY":"Slovenia","M_COUNTRY_NUMBER":"001","M_LOCALE_PUBLISH_Y_N":"1","M_COUNTRY_CODE":"SI","M_LANGUAGE_ISO":"sl","M_SLUG":"si","M_CONTENT_ORIENTATION":"ltr","M_LANGUAGE_NATIVE":"Slovenščina"},{"COMMON_ID":"locale002","M_HREFLANG_CODE":"hr-HR","M_COUNTRY_NATIVE":"Hrvatska","M_COUNTRY":"Croatia","M_COUNTRY_NUMBER":"002","M_LOCALE_PUBLISH_Y_N":"1","M_COUNTRY_CODE":"HR","M_LANGUAGE_ISO":"hr","M_SLUG":"hr","M_CONTENT_ORIENTATION":"ltr","M_LANGUAGE_NATIVE":"Hrvatski"},{"COMMON_ID":"locale003","M_HREFLANG_CODE":"es-ES","M_COUNTRY_NATIVE":"España","M_COUNTRY":"Spain","M_COUNTRY_NUMBER":"003","M_LOCALE_PUBLISH_Y_N":"1","M_COUNTRY_CODE":"ES","M_LANGUAGE_ISO":"es","M_SLUG":"es","M_CONTENT_ORIENTATION":"ltr","M_LANGUAGE_NATIVE":"Español"},{"COMMON_ID":"locale004","M_HREFLANG_CODE":"fr-FR","M_COUNTRY_NATIVE":"France","M_COUNTRY":"France","M_COUNTRY_NUMBER":"004","M_LOCALE_PUBLISH_Y_N":"1","M_COUNTRY_CODE":"FR","M_LANGUAGE_ISO":"fr","M_SLUG":"fr","M_CONTENT_ORIENTATION":"ltr","M_LANGUAGE_NATIVE":"Français"},{"COMMON_ID":"locale005","M_HREFLANG_CODE":"de-DE","M_COUNTRY_NATIVE":"Deutschland","M_COUNTRY":"Germany","M_COUNTRY_NUMBER":"005","M_LOCALE_PUBLISH_Y_N":"1","M_COUNTRY_CODE":"DE","M_LANGUAGE_ISO":"de","M_SLUG":"de","M_CONTENT_ORIENTATION":"ltr","M_LANGUAGE_NATIVE":"Deutsch"}]